data_repos/countries.json
data_repos/iris.csv
data_repos/read.py
data_repos-1.0.0.dist-info/LICENSE
data_repos-1.0.0.dist-info/METADATA
data_repos-1.0.0.dist-info/WHEEL
data_repos-1.0.0.dist-info/top_level.txt
data_repos-1.0.0.dist-info/RECORD
