Metadata-Version: 2.1
Name: data-repos
Version: 1.0.0
Summary: A namespace package for data files
Author-email: Real Python <info@realpython.com>, Ian Currie <iansedano@gmail.com>, Geir Arne Hjelle <geirarne@gmail.com>
License: MIT
Project-URL: Homepage, https://realpython.com/python-namespace-package/
Project-URL: Source Code, https://github.com/realpython/data-repos/
Project-URL: Tutorial, https://realpython.com/python-namespace-package/
Keywords: namespace,data
Classifier: Intended Audience :: Developers
Classifier: License :: OSI Approved :: MIT License
Classifier: Natural Language :: English
Classifier: Operating System :: MacOS
Classifier: Operating System :: Microsoft
Classifier: Operating System :: POSIX :: Linux
Classifier: Programming Language :: Python :: 3.7
Classifier: Programming Language :: Python :: 3.8
Classifier: Programming Language :: Python :: 3.9
Classifier: Programming Language :: Python :: 3.10
Classifier: Programming Language :: Python :: 3.11
Classifier: Topic :: Education
Classifier: Topic :: Software Development :: Libraries :: Python Modules
Requires-Python: >=3.7
License-File: LICENSE
Requires-Dist: pandas
Provides-Extra: dev
Requires-Dist: black ; extra == 'dev'
Requires-Dist: bump2version ; extra == 'dev'
Requires-Dist: ruff ; extra == 'dev'
Requires-Dist: interrogate ; extra == 'dev'
Requires-Dist: isort ; extra == 'dev'
Provides-Extra: test
Requires-Dist: black ; extra == 'test'
Requires-Dist: ruff ; extra == 'test'
Requires-Dist: interrogate ; extra == 'test'
Requires-Dist: pytest ; extra == 'test'
Requires-Dist: pytest-cov ; extra == 'test'
Requires-Dist: tox ; extra == 'test'
